benchmarkcr/__init__.py
benchmarkcr/analysis.py
benchmarkcr/logging_config.py
benchmarkcr/plotting.py
benchmarkcr/preprocessing.py
benchmarkcr/utils.py
benchmarkcr/data/dataset/liver_cell_lines_500_genes.csv
benchmarkcr/data/dataset/melanoma_cell_lines_500_genes.csv
benchmarkcr/data/dataset/neuroblastoma_cell_lines_500_genes.csv
benchmarkcr/data/gold_standard/CORUM.p
benchmarkcr/data/gold_standard/GOBP.p
benchmarkcr/data/gold_standard/PATHWAY.p
benchmarkcr/data/gold_standard/corum.csv
benchmarkcr/data/gold_standard/gobp.csv
benchmarkcr/data/gold_standard/pathway.csv
benchmarkcr/examples/basic_usage.py
benchmarkcr/examples/demo.ipynb
benchmarkcr-0.1.0.dist-info/METADATA
benchmarkcr-0.1.0.dist-info/WHEEL
benchmarkcr-0.1.0.dist-info/entry_points.txt
benchmarkcr-0.1.0.dist-info/RECORD
