Metadata-Version: 2.4
Name: benchmarkCR
Version: 0.1.0
Summary: benchmarkCR (systematic CRISPR screen benchmarking framework) is a benchmarking toolkit for evaluating CRISPR screen results against biological gold standards. The toolkit computes gene-level and complex-level performance metrics, helping researchers systematically assess the biological relevance and resolution of their CRISPR screening data.
Author-email: Yasir Demirtaş <tyasird@hotmail.com>
Requires-Python: >=3.8
Requires-Dist: adjusttext
Requires-Dist: art
Requires-Dist: bitarray
Requires-Dist: emoji
Requires-Dist: joblib
Requires-Dist: loguru
Requires-Dist: matplotlib
Requires-Dist: numpy<2.1,>=1.22
Requires-Dist: pandas
Requires-Dist: pyarrow
Requires-Dist: python-slugify
Requires-Dist: scikit-learn
Requires-Dist: scipy
Requires-Dist: tqdm
